[{"title":"Test Title","text":"Test text","id":"0"},{"title":"Testers","text":"Testers","id":"1"},{"title":"Tester","text":"Tester","id":"2"},{"title":"test","text":"Test","id":"3"},{"title":"New Note","text":"New Note","id":"4"},{"title":"hhh","text":"hhh","id":"5"},{"title":"Test","text":"Test","id":"6"},{"title":"Test","text":"Test","id":"7"},{"title":"Tests","text":"Test","id":"8"},{"title":"Test","text":"Test","id":"9"},{"title":"Mytest","text":"Mytest","id":"10"},{"title":"Tester","text":"Tester","id":"11"},{"title":"Testing again","text":"Test","id":"12"},{"title":"Testing again","text":"Test","id":"13"},{"title":"Testing again","text":"Test","id":"14"},{"title":"Testing again","text":"Test","id":"15"},{"title":"Testing again","text":"Test","id":"16"},{"title":"Testing again","text":"Test","id":"17"},{"title":"Testing ","text":"Testing ","id":"18"},{"title":"Test","text":"Test","id":"19"},{"title":"Christal's Notes","text":"Notes ","id":"20"},{"title":"Test","text":"Test","id":"21"},{"title":"New Note ","text":"I need help","id":"22"},{"title":"Test","text":"Test"}]